setup.py
rssfilter/__init__.py
rssfilter.egg-info/PKG-INFO
rssfilter.egg-info/SOURCES.txt
rssfilter.egg-info/dependency_links.txt
rssfilter.egg-info/entry_points.txt
rssfilter.egg-info/top_level.txt