Metadata-Version: 1.1
Name: rssfilter
Version: 0.0.1
Summary: Fetch, filter, and re-render RSS feeds for more useful consumption.
Home-page: http://github.com/cathalgarvey/rssfilter
Author: Cathal Garvey
Author-email: cathalgarvey@cathalgarvey.me
License: AGPL
Keywords: rss,atom,feed,subscription,filter,regex,web,news
Platform: UNKNOWN
Classifier: Development Status :: 4 - Beta
Classifier: Intended Audience :: Developers
Classifier: License :: OSI Approved :: GNU General Public License (GPL)
Classifier: Programming Language :: Python
Classifier: Programming Language :: Python :: 3.3
Classifier: Programming Language :: Python :: 3.4
Classifier: Topic :: Software Development :: Libraries :: Python Modules
Classifier: Topic :: Text Processing
Classifier: Topic :: Utilities
Requires: feedgenerator
Requires: feedparser
Requires: bs4
Requires: lxml
